[
 {
  "start" : 20,
  "end"   : 25
 },
 {
  "start" : 28,
  "end"   : 29
 },
 {
  "start" : 38,
  "end"   : 45
 },
 {
  "start" : 99,
  "end"   : 102
 },
 {
  "start" : 106,
  "end"   : 123
 },
 {
  "start" : 124,
  "end"   : 126
 },
 {
  "start" : 129,
  "end"   : 140
 },
 {
  "start" : 201,
  "end"   : 210
 },
 {
  "start" : 212,
  "end"   : 214
 },
 {
  "start" : 301,
  "end"   : 303
 },
 {
  "start" : 304,
  "end"   : 309
 },
 {
  "start" : 310,
  "end"   : 311
 },
 {
  "start" : 312,
  "end"   : 330
 },
 {
  "start" : 460,
  "end"   : 465
 },
 {
  "start" : 620,
  "end"   : 623
 },
 {
  "start" : 650,
  "end"   : 652
 },
 {
  "start" : 802,
  "end"   : 850
 },
 {
  "start" : 863,
  "end"   : 869
 },
 {
  "start" : 943,
  "end"   : 988
 }
]
